condAPI/__init__.py
condAPI/__main__.py
condAPI/endpoints/__init__.py
condAPI/endpoints/root.py
condAPI/endpoints/schema.py
condapi-1.0.1.dist-info/LICENSE
condapi-1.0.1.dist-info/METADATA
condapi-1.0.1.dist-info/WHEEL
condapi-1.0.1.dist-info/entry_points.txt
condapi-1.0.1.dist-info/RECORD
