Metadata-Version: 2.1
Name: condAPI
Version: 1.0.1
Summary: condAPI is a FastAPI-based application designed to manage and validate JSON schemas.
Home-page: https://github.com/guillerch/condAPI
License: MIT
Keywords: fastapi,api,condAPI
Author: GuillerCH
Author-email: guillerc33@gmail.com
Requires-Python: >=3.8,<4.0
Classifier: License :: OSI Approved :: MIT License
Classifier: Programming Language :: Python :: 3
Classifier: Programming Language :: Python :: 3.8
Classifier: Programming Language :: Python :: 3.9
Classifier: Programming Language :: Python :: 3.10
Classifier: Programming Language :: Python :: 3.11
Classifier: Programming Language :: Python :: 3.12
Classifier: Programming Language :: Python :: 3.13
Requires-Dist: fastapi (>=0.68.0,<0.69.0)
Requires-Dist: httpx (>=0.19.0,<0.20.0)
Requires-Dist: pydantic (>=1.8.2,<2.0.0)
Requires-Dist: uvicorn (>=0.15.0,<0.16.0)
Project-URL: Repository, https://github.com/guillerch/condAPI
